LICENSE
README.md
setup.py
request_logger/__init__.py
request_logger/admin.py
request_logger/apps.py
request_logger/models.py
request_logger/tests.py
request_logger/views.py
request_logger.egg-info/PKG-INFO
request_logger.egg-info/SOURCES.txt
request_logger.egg-info/dependency_links.txt
request_logger.egg-info/top_level.txt
request_logger/middleware/request_logger.py
request_logger/migrations/0001_initial.py
request_logger/migrations/__init__.py