Metadata-Version: 2.1
Name: request-logger
Version: 1.2
Home-page: https://github.com/EmreTurkmen-Hub/request-logger
Author: Emre Türkmen
Author-email: emre@parsyazilim.com
Classifier: Programming Language :: Python :: 3
Classifier: License :: OSI Approved :: MIT License
Classifier: Operating System :: OS Independent
License-File: LICENSE
